monas-0.2.1.dist-info/METADATA
monas-0.2.1.dist-info/WHEEL
monas-0.2.1.dist-info/entry_points.txt
monas-0.2.1.dist-info/licenses/LICENSE
monas/__init__.py
monas/__main__.py
monas/cli.py
monas/commands/__init__.py
monas/commands/add.py
monas/commands/bump.py
monas/commands/changed.py
monas/commands/common.py
monas/commands/init.py
monas/commands/install.py
monas/commands/list.py
monas/commands/new.py
monas/commands/publish.py
monas/commands/remove.py
monas/config.py
monas/metadata/__init__.py
monas/metadata/base.py
monas/metadata/pep621.py
monas/metadata/setupcfg.py
monas/project.py
monas/questions.py
monas/utils.py
monas/vcs.py
monas-0.2.1.dist-info/RECORD
