Metadata-Version: 2.1
Name: monas
Version: 0.2.1
Summary: Python monorepo made easy
Author-Email: Frost Ming <mianghong@gmail.com>
License: MIT
Classifier: Development Status :: 3 - Alpha
Classifier: Intended Audience :: Developers
Classifier: Programming Language :: Python :: 3
Classifier: Programming Language :: Python :: 3.7
Classifier: Programming Language :: Python :: 3.8
Classifier: Programming Language :: Python :: 3.9
Classifier: Programming Language :: Python :: 3.10
Project-URL: Repository, https://github.com/frostming/monas
Project-URL: Homepage, https://github.com/frostming/monas
Requires-Python: >=3.8
Requires-Dist: gitpython>=3
Requires-Dist: click>=7
Requires-Dist: packaging>=20
Requires-Dist: questionary
Requires-Dist: rich-click>=1.3.0
Requires-Dist: twine
Requires-Dist: tomlkit>=0.8
Requires-Dist: virtualenv>=20.1.0
Requires-Dist: parver
